cello/__init__.py
run_cello-0.1.7.dist-info/METADATA
run_cello-0.1.7.dist-info/WHEEL
run_cello-0.1.7.dist-info/entry_points.txt
run_cello-0.1.7.dist-info/top_level.txt
run_cello-0.1.7.dist-info/RECORD
