Metadata-Version: 2.1
Name: run-cello
Version: 0.1.7
Summary: Find protein sub-cellular location in FASTA files using Cello.
Home-page: UNKNOWN
Author: Frederico Schmitt Kremer
Author-email: fred.s.kremer@gmail.com
License: UNKNOWN
Keywords: bioinformatics
Platform: UNKNOWN
Requires-Dist: pandas
Requires-Dist: biopython
Requires-Dist: requests
Requires-Dist: tqdm
